ccdl/__init__.py
ccdl/binb.py
ccdl/comic_action.py
ccdl/comic_earthstar.py
ccdl/comic_walker.py
ccdl/ganma.py
ccdl/urasunday.py
ccdl/utils.py
ccdl-0.1.11.dist-info/LICENSE
ccdl-0.1.11.dist-info/METADATA
ccdl-0.1.11.dist-info/WHEEL
ccdl-0.1.11.dist-info/top_level.txt
ccdl-0.1.11.dist-info/RECORD
