Metadata-Version: 2.1
Name: ccdl
Version: 0.1.11
Summary: Online comic downloader
Home-page: https://github.com/vircoys/ccdl
Author: vircoys
Author-email: vircoys@gmail.com
License: unlicense
Platform: UNKNOWN
Classifier: Programming Language :: Python :: 3
Classifier: License :: Public Domain
Classifier: Operating System :: OS Independent
Requires-Python: >=3.6
Requires-Dist: lxml
Requires-Dist: numpy
Requires-Dist: Pillow
Requires-Dist: requests
Requires-Dist: selenium
Requires-Dist: pyexecjs
